fileToConfig/__init__.py
fileToConfig/convert.py
fileToConfigJson-0.0.1.dist-info/LICENSE
fileToConfigJson-0.0.1.dist-info/METADATA
fileToConfigJson-0.0.1.dist-info/WHEEL
fileToConfigJson-0.0.1.dist-info/top_level.txt
fileToConfigJson-0.0.1.dist-info/RECORD
